[
  {
    "key": "ctrl+cmd+up",
    "command": "editor.action.insertCursorAbove",
    "when": "editorTextFocus"
  },
  {
    "key": "alt+cmd+up",
    "command": "-editor.action.insertCursorAbove",
    "when": "editorTextFocus"
  },
  {
    "key": "ctrl+cmd+down",
    "command": "editor.action.insertCursorBelow",
    "when": "editorTextFocus"
  },
  {
    "key": "alt+cmd+down",
    "command": "-editor.action.insertCursorBelow",
    "when": "editorTextFocus"
  },
  {
    "key": "cmd+d",
    "command": "editor.action.addSelectionToNextFindMatch",
    "when": "editorTextFocus"
  },
  {
    "key": "cmd+d",
    "command": "-editor.action.addSelectionToNextFindMatch",
    "when": "editorFocus"
  },
  {
    "key": "shift+cmd+d",
    "command": "workbench.action.splitEditorDown",
    "when": "editorFocus && !editorHasSelection"
  },
  {
    "key": "shift+cmd+d",
    "command": "-mssql.disconnect",
    "when": "editorTextFocus && editorLangId == 'sql'"
  },
  {
    "key": "shift+cmd+d",
    "command": "-workbench.view.debug"
  },
  {
    "key": "cmd+d",
    "command": "workbench.action.splitEditor",
    "when": "editorFocus && !editorHasSelection"
  },
  {
    "key": "cmd+\\",
    "command": "-workbench.action.splitEditor"
  },
  {
    "key": "cmd+\\",
    "command": "workbench.action.splitEditorOrthogonal"
  },
  {
    "key": "cmd+k cmd+\\",
    "command": "-workbench.action.splitEditorOrthogonal"
  },
  {
    "key": "cmd+d",
    "command": "workbench.action.terminal.split",
    "when": "terminalFocus"
  },
  {
    "key": "cmd+\\",
    "command": "-workbench.action.terminal.split",
    "when": "terminalFocus"
  },
  {
    "key": "ctrl+shift+5",
    "command": "-workbench.action.terminal.split",
    "when": "terminalFocus"
  },
  {
    "key": "alt+j",
    "command": "workbench.action.terminal.focus",
    "when": "editorFocus"
  },
  {
    "key": "alt+k",
    "command": "workbench.action.focusFirstEditorGroup",
    "when": "terminalFocus"
  },
  {
    "key": "alt+k",
    "command": "workbench.action.focusAboveGroup",
    "when": "editorFocus"
  },
  {
    "key": "alt+l",
    "command": "-toggleFindInSelection",
    "when": "editorFocus"
  },
  {
    "key": "alt+l",
    "command": "workbench.action.focusNextGroup",
    "when": "editorFocus"
  },
  {
    "key": "alt+h",
    "command": "workbench.action.focusPreviousGroup",
    "when": "editorFocus"
  },
  {
    "key": "alt+l",
    "command": "workbench.action.terminal.focusNextPane",
    "when": "terminalFocus"
  },
  {
    "key": "alt+h",
    "command": "workbench.action.terminal.focusPreviousPane",
    "when": "terminalFocus"
  },
  {
    "key": "cmd+k shift+cmd+right",
    "command": "-workbench.action.moveEditorRightInGroup"
  },
  {
    "key": "shift+alt+right",
    "command": "workbench.action.moveEditorToRightGroup"
  },
  {
    "key": "shift+alt+left",
    "command": "workbench.action.moveEditorToLeftGroup"
  },
  {
    "key": "shift+alt+down",
    "command": "workbench.action.moveActiveEditorGroupDown"
  },
  {
    "key": "cmd+k down",
    "command": "-workbench.action.moveActiveEditorGroupDown"
  },
  {
    "key": "shift+alt+up",
    "command": "workbench.action.moveActiveEditorGroupUp"
  },
  {
    "key": "cmd+k up",
    "command": "-workbench.action.moveActiveEditorGroupUp"
  },
]
